MANIFEST.in
readme.md
requirements.txt
setup.cfg
setup.py
LessHash_BloomFilter.egg-info/PKG-INFO
LessHash_BloomFilter.egg-info/SOURCES.txt
LessHash_BloomFilter.egg-info/dependency_links.txt
LessHash_BloomFilter.egg-info/top_level.txt
lhbf/__init__.py
lhbf/bloom.py
lhbf/hash_function.py