Metadata-Version: 2.1
Name: LessHash-BloomFilter
Version: 0.0.4
Summary: Fast Bloom Filter
Home-page: https://github.com/garawalid/LH-BloomFilter
Maintainer: Walid Gara
Maintainer-email: 
License: Apache License v2
Download-URL: https://github.com/garawalid/LH-BloomFilter/archive/v0.0.4.tar.gz
Platform: UNKNOWN
